pushbullet/__init__.py
pushbullet/pushbullet.py
pushbullet_python-1.7.0.dist-info/LICENSE
pushbullet_python-1.7.0.dist-info/METADATA
pushbullet_python-1.7.0.dist-info/WHEEL
pushbullet_python-1.7.0.dist-info/top_level.txt
pushbullet_python-1.7.0.dist-info/RECORD
