Metadata-Version: 2.1
Name: pushbullet-python
Version: 1.7.0
Summary: A Python wrapper around the Pushbullet API.
Home-page: https://github.com/EinGuterWaran/pushbullet-python
Author: Janu Lingeswaran
Author-email: <janu@lingeswaran.com>
License: MIT License
Keywords: python,push bullet,push,bullet,push notifications,push notification,API wrapper
Platform: UNKNOWN
Classifier: Development Status :: 5 - Production/Stable
Classifier: License :: OSI Approved :: MIT License
Classifier: Intended Audience :: Developers
Classifier: Programming Language :: Python :: 3
Classifier: Operating System :: Unix
Classifier: Operating System :: MacOS :: MacOS X
Classifier: Operating System :: Microsoft :: Windows
Requires-Dist: requests
